nac_validate/__init__.py
nac_validate/__main__.py
nac_validate/exceptions.py
nac_validate/validator.py
nac_validate/cli/__init__.py
nac_validate/cli/defaults.py
nac_validate/cli/main.py
nac_validate-1.1.0.dist-info/METADATA
nac_validate-1.1.0.dist-info/WHEEL
nac_validate-1.1.0.dist-info/entry_points.txt
nac_validate-1.1.0.dist-info/licenses/LICENSE
nac_validate-1.1.0.dist-info/RECORD
