Metadata-Version: 2.4
Name: nac-validate
Version: 1.1.0
Summary: A CLI tool to perform syntactic and semantic validation of YAML files.
Project-URL: homepage, https://github.com/netascode/nac-validate
Project-URL: repository, https://github.com/netascode/nac-validate
Project-URL: documentation, https://github.com/netascode/nac-validate
Author-email: Daniel Schmidt <danischm@cisco.com>
Maintainer-email: Daniel Schmidt <danischm@cisco.com>
License: MPL-2.0
License-File: LICENSE
Keywords: automation,cli,testing,validation,yaml
Classifier: Development Status :: 5 - Production/Stable
Classifier: Environment :: Console
Classifier: Intended Audience :: Developers
Classifier: License :: OSI Approved :: Mozilla Public License 2.0 (MPL 2.0)
Classifier: Operating System :: OS Independent
Classifier: Programming Language :: Python :: 3
Classifier: Programming Language :: Python :: 3.10
Classifier: Programming Language :: Python :: 3.11
Classifier: Programming Language :: Python :: 3.12
Classifier: Programming Language :: Python :: 3.13
Classifier: Topic :: Software Development :: Testing
Requires-Python: >=3.10
Requires-Dist: nac-yaml>=1.1.1
Requires-Dist: ruamel-yaml>=0.18.15
Requires-Dist: typer>=0.17.4
Requires-Dist: yamale>=6.0.0
Provides-Extra: dev
Requires-Dist: ansible-core>=2.17.6; extra == 'dev'
Requires-Dist: bandit[toml]>=1.8.6; extra == 'dev'
Requires-Dist: mypy>=1.17.1; extra == 'dev'
Requires-Dist: pre-commit>=4.3.0; extra == 'dev'
Requires-Dist: pytest-cov>=6.2.1; extra == 'dev'
Requires-Dist: pytest-mock>=3.15.0; extra == 'dev'
Requires-Dist: pytest>=8.4.2; extra == 'dev'
Requires-Dist: ruff>=0.12.12; extra == 'dev'
